{
    "conditions": [
        {
            "type": "aeadditions:mod_integration",
            "mod": "mekanismgas"
        }
    ],
    "result": {
        "item": "aeadditions:part.base",
		"data": 4
    },
    "type": "forge:ore_shaped",
    "pattern": [
        "aba",
        "cdc"
    ],
    "key": {
        "a": {
			"item": "#aeadditions:iron"
        },
		"b": {
			"item": "#aeadditions:annihilationCore"
		},
		"c": {
			"item": "#aeadditions:flower"
		},
		"d": {
			"item": "minecraft:sticky_piston"
		}
    }
}